CONTRIBUTORS.txt
MANIFEST.in
README.rst
requirements.txt
setup.py
tox.ini
gipsy/__init__.py
gipsy/modeltranslation/__init__.py
gipsy/modeltranslation/sections/__init__.py
gipsy/modeltranslation/sections/admin.py
gipsy/modeltranslation/sections/apps.py
gipsy/modeltranslation/sections/forms.py
gipsy/modeltranslation/sections/managers.py
gipsy/modeltranslation/sections/models.py
gipsy/modeltranslation/sections/tests.py
gipsy/modeltranslation/sections/translation.py
gipsy/modeltranslation/sections/views.py
gipsy/modeltranslation/sections/migrations/0001_initial.py
gipsy/modeltranslation/sections/migrations/0002_auto_20150821_1003.py
gipsy/modeltranslation/sections/migrations/__init__.py
gipsy_modeltranslation_sections.egg-info/PKG-INFO
gipsy_modeltranslation_sections.egg-info/SOURCES.txt
gipsy_modeltranslation_sections.egg-info/dependency_links.txt
gipsy_modeltranslation_sections.egg-info/namespace_packages.txt
gipsy_modeltranslation_sections.egg-info/requires.txt
gipsy_modeltranslation_sections.egg-info/top_level.txt
requirements/base.txt
requirements/dev.txt
requirements/production.txt
requirements/test.txt